SwarmML/AlgorithmPSO.py
SwarmML/FeatureSelection.py
SwarmML/__init__.py
SwarmML-1.0.dist-info/METADATA
SwarmML-1.0.dist-info/WHEEL
SwarmML-1.0.dist-info/top_level.txt
SwarmML-1.0.dist-info/RECORD
