Metadata-Version: 2.1
Name: SwarmML
Version: 1.0
Summary: Feature Selection with PSO
Home-page: https://github.com/SalehAhmad1/SwarmML
Author: Saleh Ahmad
Author-email: salehahmad2106@gmail.com
License: UNKNOWN
Keywords: feature selection,particle swarm optimization,PSO,machine learning,data science
Platform: UNKNOWN
Classifier: Intended Audience :: Developers
Classifier: License :: OSI Approved :: MIT License
Classifier: Operating System :: OS Independent
Classifier: Programming Language :: Python
Requires-Dist: numpy
Requires-Dist: pandas
Requires-Dist: readme-md
Requires-Dist: sklearn
